{
    "projects" : [
        
        {
            "image" : "images/projects/net.png",
            "title": "Visitor Management System",
            "bodyText": "- A Multitenancy Django web and flutter mobile application for Building Management, Real estate Management and Visitor management\n -  Real-time Chat Capabilities\n - Invoice Generation\n - Users: - Building Owner, Company Admin, Employees, Security.\n - Generating QR Codes and scanning. \n - Real Estate.\n Parking Management".,
           
            "tags" : [
                "Python - Django",
                "JQUERY",
                "CSS",
                "JavaScript",
                "Postgress"
            ]
        },
        {
            "image" : "images/projects/mern.png",
            "title": "MERN Shopping List",
            "bodyText": "- Simple Shopping List application built using Express, React, and Node.js. It allows users to add items and their prices.",
            "links": [
                {
                    "text": "GitHub",
                    "href": "https://github.com/Aduda-Shem/MERN-Shopping-List"
             
                }
            ],
            "tags" : [
                "React",
                "NodeJS",
                "CSS"
            ]
        },
        {
            "image" : "images/projects/cooling.png",
            "title": "Cooling-system-LTD-mobile-application-and-web-admin-interface",
            "bodyText": "- A Mobile and a Web based application system for a cooling system\n -  Login: Users can create an account or sign in to an existing account using their email and password.\n - Dashboard: Provides an overview of all users and their registration status.\n - Settings: Allows admins to manage user accounts and customize system settings.",
            "links": [
                {
                    "text": "GitHub",
                    "href": "https://github.com/Aduda-Shem/Cooling-system-LTD-mobile-application-and-web-admin-interface"
                },
                {
                    "text": "Live",
                    "href": "https://granhmtechbytes.000webhostapp.com/northstar/admin/login.php"
                }
            ],
            "tags" : [
                "Java",
                "PHP",
                "CSS",
                "JavaScript"
            ]
        },     

        {
            "image" : "images/projects/goal.png",
            "title": "React - Goal - List",
            "bodyText": "- simple web application built with React and styled with CSS.\n - It allows users to create and track their goals.\n\n\n",
            "links": [
                {
                    "text": "GitHub",
                    "href": "https://github.com/Aduda-Shem/react-goal-list"
                },
                {
                    "text":"Live",
                    "href": "https://react-goal-list.vercel.app/"
                }
            ],
            "tags" : [
                "React",
                "JavaScript",
                "HTML",
                "CSS"
            ]
        },
        {
            "image" : "images/projects/young.png",
            "title": "Young-tech-course",
            "bodyText": "- A Web App that consumes data from https://jsonplaceholder.typicode.com\n - Utilizes React and NodeJS\n - The Stylings are designed in Bootstrap and CSS\n\n",
            "links": [
                {
                    "text": "GitHub",
                    "href": "https://github.com/Aduda-Shem/young-tech-course"
                },
                {
                    "text":"Live",
                    "href": "https://granhm.vercel.app/"
                }
            ],
            "tags" : [
                "React",
                "NodeJS",
                "JSONPlaceholder",
                "CSS",
                "Bootstrap"
            ]
        },
        {
            "image" : "images/projects/daydream.png",
            "title": "Music-Playmate",
            "bodyText": "- Simple music player application that allows users to play music from their local machine.\n",
            "links": [
                {
                    "text": "GitHub",
                    "href": "https://github.com/Aduda-Shem/Music-Playmate"
                }
            ],
            "tags" : [
                "JavaScript",
                "HTML",
                "CSS"
            ]
        },
        {
            "image" : "images/projects/schedule.jpg",
            "title": "Schedule App",
            "bodyText": "- Android app in kotlin for scheduling tasks.\n",
            "links": [
                {
                    "text": "GitHub",
                    "href": "https://github.com/Aduda-Shem/ScheduleApp"
                }
            ],
            "tags" : [
                "Kotlin"
            ]
        }
    ]
}
